{"article": [5, "/categories/article.html", {"posts": [{"date": "12/10/2015", "isodate": "2015-12-10T00:01:58+13:00", "title": "devmob15-reflection", "url": "/posts/devmob15-reflection.html"}, {"date": "12/04/2015", "isodate": "2015-12-04T16:18:26+13:00", "title": "will-tlc", "url": "/posts/will-tlc.html"}, {"date": "12/03/2015", "isodate": "2015-12-03T00:01:58+13:00", "title": "nzdevmob2015", "url": "/posts/nzdevmob2015.html"}, {"date": "12/02/2015", "isodate": "2015-12-02T00:01:58+13:00", "title": "kiwipycon-travelbac", "url": "/posts/kiwipycon-travelbac.html"}, {"date": "12/01/2015", "isodate": "2015-12-01T00:01:58+13:00", "title": "kiwipycon2015", "url": "/posts/kiwipycon2015.html"}]}], "conference": [4, "/categories/conference.html", {"posts": [{"date": "12/10/2015", "isodate": "2015-12-10T00:01:58+13:00", "title": "devmob15-reflection", "url": "/posts/devmob15-reflection.html"}, {"date": "12/03/2015", "isodate": "2015-12-03T00:01:58+13:00", "title": "nzdevmob2015", "url": "/posts/nzdevmob2015.html"}, {"date": "12/02/2015", "isodate": "2015-12-02T00:01:58+13:00", "title": "kiwipycon-travelbac", "url": "/posts/kiwipycon-travelbac.html"}, {"date": "12/01/2015", "isodate": "2015-12-01T00:01:58+13:00", "title": "kiwipycon2015", "url": "/posts/kiwipycon2015.html"}]}], "creative commons": [2, "/categories/creative-commons.html", {"posts": [{"date": "03/29/2016", "isodate": "2016-03-29T00:01:58+13:00", "title": "peppercarrot10", "url": "/posts/peppercarrot10.html"}, {"date": "03/28/2016", "isodate": "2016-03-28T00:01:58+13:00", "title": "peppercarrot09", "url": "/posts/peppercarrot09.html"}]}], "disney": [1, "/categories/disney.html", {"posts": [{"date": "03/25/2016", "isodate": "2016-03-25T00:01:58+13:00", "title": "downout", "url": "/posts/downout.html"}]}], "doctorow": [5, "/categories/doctorow.html", {"posts": [{"date": "03/30/2016", "isodate": "2016-03-30T00:01:58+13:00", "title": "est", "url": "/posts/est.html"}, {"date": "03/28/2016", "isodate": "2016-03-28T00:01:58+13:00", "title": "overclocked", "url": "/posts/overclocked.html"}, {"date": "03/27/2016", "isodate": "2016-03-27T00:01:58+13:00", "title": "someone", "url": "/posts/someone.html"}, {"date": "03/26/2016", "isodate": "2016-03-26T00:01:58+13:00", "title": "ftw", "url": "/posts/ftw.html"}, {"date": "03/25/2016", "isodate": "2016-03-25T00:01:58+13:00", "title": "downout", "url": "/posts/downout.html"}]}], "letter": [2, "/categories/letter.html", {"posts": [{"date": "04/02/2016", "isodate": "2016-04-02T15:01:58+13:00", "title": "campnanowrimo16-day02", "url": "/posts/campnanowrimo-day02.html"}, {"date": "04/01/2016", "isodate": "2016-04-01T15:01:58+13:00", "title": "campnanowrimo16-day01", "url": "/posts/campnanowrimo-day01.html"}]}], "novel": [19, "/categories/novel.html", {"posts": [{"date": "04/02/2016", "isodate": "2016-04-02T15:01:58+13:00", "title": "campnanowrimo16-day02", "url": "/posts/campnanowrimo-day02.html"}, {"date": "04/01/2016", "isodate": "2016-04-01T15:01:58+13:00", "title": "campnanowrimo16-day01", "url": "/posts/campnanowrimo-day01.html"}, {"date": "03/31/2016", "isodate": "2016-03-31T12:01:58+13:00", "title": "peppercarrot12", "url": "/posts/peppercarrot12.html"}, {"date": "03/30/2016", "isodate": "2016-03-30T12:01:58+13:00", "title": "peppercarrot11", "url": "/posts/peppercarrot11.html"}, {"date": "03/30/2016", "isodate": "2016-03-30T00:01:58+13:00", "title": "est", "url": "/posts/est.html"}, {"date": "03/29/2016", "isodate": "2016-03-29T00:01:58+13:00", "title": "peppercarrot10", "url": "/posts/peppercarrot10.html"}, {"date": "03/28/2016", "isodate": "2016-03-28T00:01:58+13:00", "title": "overclocked", "url": "/posts/overclocked.html"}, {"date": "03/28/2016", "isodate": "2016-03-28T00:01:58+13:00", "title": "peppercarrot09", "url": "/posts/peppercarrot09.html"}, {"date": "03/27/2016", "isodate": "2016-03-27T00:01:58+13:00", "title": "someone", "url": "/posts/someone.html"}, {"date": "03/26/2016", "isodate": "2016-03-26T00:01:58+13:00", "title": "ftw", "url": "/posts/ftw.html"}, {"date": "03/25/2016", "isodate": "2016-03-25T00:01:58+13:00", "title": "downout", "url": "/posts/downout.html"}, {"date": "03/21/2016", "isodate": "2016-03-21T00:01:58+13:00", "title": "peppercarrot08", "url": "/posts/peppercarrot08.html"}, {"date": "03/20/2016", "isodate": "2016-03-20T00:01:58+13:00", "title": "peppercarrot07", "url": "/posts/peppercarrot07.html"}, {"date": "03/19/2016", "isodate": "2016-03-19T00:01:58+13:00", "title": "peppercarrot06", "url": "/posts/peppercarrot06.html"}, {"date": "03/15/2016", "isodate": "2016-03-15T00:01:58+13:00", "title": "peppercarrot05", "url": "/posts/peppercarrot05.html"}, {"date": "03/14/2016", "isodate": "2016-03-14T00:01:58+13:00", "title": "peppercarrot04", "url": "/posts/peppercarrot04.html"}, {"date": "03/13/2016", "isodate": "2016-03-13T00:01:58+13:00", "title": "peppercarrot03", "url": "/posts/peppercarrot03.html"}, {"date": "03/10/2016", "isodate": "2016-03-10T00:01:58+13:00", "title": "peppercarrot02", "url": "/posts/peppercarrot02.html"}, {"date": "03/09/2016", "isodate": "2016-03-09T00:01:58+13:00", "title": "peppercarrot01", "url": "/posts/peppercarrot01.html"}]}], "peppercarrot": [14, "/categories/peppercarrot.html", {"posts": [{"date": "04/02/2016", "isodate": "2016-04-02T15:01:58+13:00", "title": "campnanowrimo16-day02", "url": "/posts/campnanowrimo-day02.html"}, {"date": "04/01/2016", "isodate": "2016-04-01T15:01:58+13:00", "title": "campnanowrimo16-day01", "url": "/posts/campnanowrimo-day01.html"}, {"date": "03/31/2016", "isodate": "2016-03-31T12:01:58+13:00", "title": "peppercarrot12", "url": "/posts/peppercarrot12.html"}, {"date": "03/30/2016", "isodate": "2016-03-30T12:01:58+13:00", "title": "peppercarrot11", "url": "/posts/peppercarrot11.html"}, {"date": "03/29/2016", "isodate": "2016-03-29T00:01:58+13:00", "title": "peppercarrot10", "url": "/posts/peppercarrot10.html"}, {"date": "03/28/2016", "isodate": "2016-03-28T00:01:58+13:00", "title": "peppercarrot09", "url": "/posts/peppercarrot09.html"}, {"date": "03/21/2016", "isodate": "2016-03-21T00:01:58+13:00", "title": "peppercarrot08", "url": "/posts/peppercarrot08.html"}, {"date": "03/20/2016", "isodate": "2016-03-20T00:01:58+13:00", "title": "peppercarrot07", "url": "/posts/peppercarrot07.html"}, {"date": "03/19/2016", "isodate": "2016-03-19T00:01:58+13:00", "title": "peppercarrot06", "url": "/posts/peppercarrot06.html"}, {"date": "03/15/2016", "isodate": "2016-03-15T00:01:58+13:00", "title": "peppercarrot05", "url": "/posts/peppercarrot05.html"}, {"date": "03/14/2016", "isodate": "2016-03-14T00:01:58+13:00", "title": "peppercarrot04", "url": "/posts/peppercarrot04.html"}, {"date": "03/13/2016", "isodate": "2016-03-13T00:01:58+13:00", "title": "peppercarrot03", "url": "/posts/peppercarrot03.html"}, {"date": "03/10/2016", "isodate": "2016-03-10T00:01:58+13:00", "title": "peppercarrot02", "url": "/posts/peppercarrot02.html"}, {"date": "03/09/2016", "isodate": "2016-03-09T00:01:58+13:00", "title": "peppercarrot01", "url": "/posts/peppercarrot01.html"}]}], "python": [2, "/categories/python.html", {"posts": [{"date": "12/02/2015", "isodate": "2015-12-02T00:01:58+13:00", "title": "kiwipycon-travelbac", "url": "/posts/kiwipycon-travelbac.html"}, {"date": "12/01/2015", "isodate": "2015-12-01T00:01:58+13:00", "title": "kiwipycon2015", "url": "/posts/kiwipycon2015.html"}]}], "science fiction": [4, "/categories/science-fiction.html", {"posts": [{"date": "03/30/2016", "isodate": "2016-03-30T00:01:58+13:00", "title": "est", "url": "/posts/est.html"}, {"date": "03/28/2016", "isodate": "2016-03-28T00:01:58+13:00", "title": "overclocked", "url": "/posts/overclocked.html"}, {"date": "03/27/2016", "isodate": "2016-03-27T00:01:58+13:00", "title": "someone", "url": "/posts/someone.html"}, {"date": "03/26/2016", "isodate": "2016-03-26T00:01:58+13:00", "title": "ftw", "url": "/posts/ftw.html"}]}], "tlc": [1, "/categories/tlc.html", {"posts": [{"date": "12/04/2015", "isodate": "2015-12-04T16:18:26+13:00", "title": "will-tlc", "url": "/posts/will-tlc.html"}]}], "web": [2, "/categories/web.html", {"posts": [{"date": "12/10/2015", "isodate": "2015-12-10T00:01:58+13:00", "title": "devmob15-reflection", "url": "/posts/devmob15-reflection.html"}, {"date": "12/03/2015", "isodate": "2015-12-03T00:01:58+13:00", "title": "nzdevmob2015", "url": "/posts/nzdevmob2015.html"}]}]}